nef_pipelines/VERSION
nef_pipelines/__init__.py
nef_pipelines/__main__.py
nef_pipelines/main.py
nef_pipelines/data/ambiguity_translations.json
nef_pipelines/data/default_atom_sets_by_comp_and_linking.json
nef_pipelines/data/mmcif_nef_v1_1.dic
nef_pipelines/data/chem_comp/DNA+A+msd_ccpnRef_2007-12-11-10-13-15_00001.json
nef_pipelines/data/chem_comp/DNA+C+msd_ccpnRef_2007-12-11-10-13-16_00002.json
nef_pipelines/data/chem_comp/DNA+G+msd_ccpnRef_2007-12-11-10-13-16_00005.json
nef_pipelines/data/chem_comp/DNA+I+msd_ccpnRef_2007-12-11-10-13-17_00002.json
nef_pipelines/data/chem_comp/DNA+T+msd_ccpnRef_2007-12-11-10-13-17_00005.json
nef_pipelines/data/chem_comp/DNA+U+msd_ccpnRef_2007-12-11-10-13-17_00008.json
nef_pipelines/data/chem_comp/DNA+Xxx+pdbe_ccpnRef_2009-07-30-11-31-14-969_00001.json
nef_pipelines/data/chem_comp/RNA+A+msd_ccpnRef_2007-12-11-10-13-18_00001.json
nef_pipelines/data/chem_comp/RNA+C+msd_ccpnRef_2007-12-11-10-13-18_00004.json
nef_pipelines/data/chem_comp/RNA+G+msd_ccpnRef_2007-12-11-10-13-19_00001.json
nef_pipelines/data/chem_comp/RNA+I+msd_ccpnRef_2007-12-11-10-13-19_00004.json
nef_pipelines/data/chem_comp/RNA+T+msd_ccpnRef_2007-12-11-10-13-19_00007.json
nef_pipelines/data/chem_comp/RNA+U+msd_ccpnRef_2007-12-11-10-13-20_00001.json
nef_pipelines/data/chem_comp/RNA+Xxx+pdbe_ccpnRef_2009-07-30-11-31-15-197_00001.json
nef_pipelines/data/chem_comp/protein+Ala+msd_ccpnRef_2007-12-11-10-20-09_00022.json
nef_pipelines/data/chem_comp/protein+Arg+msd_ccpnRef_2007-12-11-10-20-10_00007.json
nef_pipelines/data/chem_comp/protein+Asn+msd_ccpnRef_2007-12-11-10-20-10_00013.json
nef_pipelines/data/chem_comp/protein+Asp+msd_ccpnRef_2007-12-11-10-20-10_00001.json
nef_pipelines/data/chem_comp/protein+Cys+msd_ccpnRef_2007-12-11-10-20-13_00005.json
nef_pipelines/data/chem_comp/protein+Gln+msd_ccpnRef_2007-12-11-10-20-15_00017.json
nef_pipelines/data/chem_comp/protein+Glu+msd_ccpnRef_2007-12-11-10-20-15_00018.json
nef_pipelines-0.1.117.dist-info/licenses/LICENSE.txt
nef_pipelines-0.1.117.dist-info/METADATA
nef_pipelines-0.1.117.dist-info/WHEEL
nef_pipelines-0.1.117.dist-info/entry_points.txt
nef_pipelines-0.1.117.dist-info/top_level.txt
nef_pipelines-0.1.117.dist-info/RECORD
