Metadata-Version: 2.4
Name: nef-pipelines
Version: 0.1.117
Summary: Tools for Manipulating NEF [NMR Exchange Format] Files and Foreign File Access
Home-page: https://github.com/varioustoxins/NEF-Pipelines
Author: varioustoxins
Author-email: g.s.thompson@kent.ac.uk
License: LGPL-2.1
Project-URL: Documentation, https://pyscaffold.org/
Platform: any
Classifier: Development Status :: 4 - Beta
Classifier: Programming Language :: Python
License-File: LICENSE.txt
Requires-Dist: importlib-metadata; python_version < "3.8"
Requires-Dist: annotated-types==0.6.0
Requires-Dist: beautifulsoup4==4.12.3
Requires-Dist: cachetools==5.3.3
Requires-Dist: click==8.1.3
Requires-Dist: f-yeah==0.3.0; python_version < "3.12"
Requires-Dist: f-yeah==0.4.0; python_version >= "3.12"
Requires-Dist: fastaparser==1.1.1
Requires-Dist: freezegun==1.1.0
Requires-Dist: frozendict==2.3.7
Requires-Dist: hjson==3.1.0
Requires-Dist: lazy_import==0.2.2
Requires-Dist: mmcif-pdbx==2.0.1
Requires-Dist: ordered-set==4.1.0
Requires-Dist: parse==1.20.1
Requires-Dist: pydantic==2.7.4
Requires-Dist: pynmrstar==3.3.4
Requires-Dist: pyparsing==3.0.8
Requires-Dist: pytest==7.1.3
Requires-Dist: pytest-mock==3.12.0
Requires-Dist: requests==2.31.0
Requires-Dist: runstats==2.0.0
Requires-Dist: StrEnum==0.4.8
Requires-Dist: tabulate==0.8.9
Requires-Dist: treelib==1.7.0
Requires-Dist: typer==0.7.0
Requires-Dist: typing-extensions==4.12.2; python_version <= "3.8"
Requires-Dist: uncertainties==3.1.7
Requires-Dist: urllib3==1.26.15
Requires-Dist: wcmatch==8.5
Requires-Dist: xmltodict==0.13.0
Provides-Extra: testing
Requires-Dist: setuptools; extra == "testing"
Requires-Dist: pytest; extra == "testing"
Dynamic: license-file
